task1/rom.sv
module rom #(
    parameter   ADDRESS_WIDTH = 8,
                DATA_WIDTH = 8
) (
    input logic clk,
    input logic [ADDRESS_WIDTH-1:0] addr,
    output logic [DATA_WIDTH-1:0] dout
);

logic [DATA_WIDTH-1:0] rom_array [2**ADDRESS_WIDTH-1:0];

initial begin
    $display("Loading ROM:");
    $readmemh("sinerom.mem", rom_array);
end;

always_ff @(posedge clk)
    // Synchronous output
    dout <= rom_array [addr];

endmodule

task2/counter.sv
module counter #(
    parameter ADDRESS_WIDTH = 8
) (
    input logic [ADDRESS_WIDTH-1:0] incr,
    input logic rst, en, clk,
    output logic [ADDRESS_WIDTH-1:0] count
);

    always_ff @(posedge clk)
        if (rst) count <= 0;
        else if (en) count <= count + incr;
        else count <= count;
endmodule

task1/sinegen.sv
module sinegen(
    input logic [7:0] incr,
    input logic rst, en, clk,
    output logic [7:0] dout
);

    logic [7:0] addr;

    counter sinegen_counter (
        .incr (incr),
        .rst (rst),
        .en (en),
        .clk (clk),
        .count (addr)
    );

    rom sinegen_rom (
        .clk (clk),
        .addr (addr),
        .dout (dout)
    );

endmodule

task1/sinegen.vcd
$version Generated by VerilatedVcd $end
$date Fri Oct 24 10:42:06 2025 $end
$timescale 1ps $end

 $scope module TOP $end
  $var wire  1 & clk $end
  $var wire  8 ' dout [7:0] $end
  $var wire  1 % en $end
  $var wire  8 # incr [7:0] $end
  $var wire  1 $ rst $end
  $scope module sinegen $end
   $var wire  8 ( addr [7:0] $end
   $var wire  1 & clk $end
   $var wire  8 ' dout [7:0] $end
   $var wire  1 % en $end
   $var wire  8 # incr [7:0] $end
   $var wire  1 $ rst $end
   $scope module sinegen_counter $end
    $var wire 32 ) ADDRESS_WIDTH [31:0] $end
    $var wire  1 & clk $end
    $var wire  8 ( count [7:0] $end
    $var wire  1 % en $end
    $var wire  8 # incr [7:0] $end
    $var wire  1 $ rst $end
   $upscope $end
   $scope module sinegen_rom $end
    $var wire 32 ) ADDRESS_WIDTH [31:0] $end
    $var wire 32 ) DATA_WIDTH [31:0] $end
    $var wire  8 ( addr [7:0] $end
    $var wire  1 & clk $end
    $var wire  8 ' dout [7:0] $end
   $upscope $end
  $upscope $end
 $upscope $end
$enddefinitions $end


#0
b00000001 #
1$
1%
1&
b00000000 '
b00000000 (
b00000000000000000000000000001000 )
#1
0&
#2
b00110011 #
0$
1&
b11111110 '
#3
0&
#4
1&
b00110011 (
#5
0&
#6
1&
b10100110 '
b01100110 (
#7
0&
#8
1&
b00011000 '
b10011001 (
#9
0&
#10
1&
b00010111 '
b11001100 (
#11
0&
#12
1&
b10100011 '
b11111111 (
#13
0&
#14
1&
b11111101 '
b00110010 (
#15
0&
#16
1&
b10101001 '
b01100101 (
#17
0&
#18
1&
b00011010 '
b10011000 (
#19
0&
#20
1&
b00010101 '
b11001011 (
#21
0&
#22
1&
b10100000 '
b11111110 (
#23
0&
#24
1&
b11111101 '
b00110001 (
#25
0&
#26
1&
b10101100 '
b01100100 (
#27
0&
#28
1&
b00011100 '
b10010111 (
#29
0&
#30
1&
b00010011 '
b11001010 (
#31
0&
#32
1&
b10011101 '
b11111101 (
#33
0&
#34
1&
b11111101 '
b00110000 (
#35
0&
#36
1&
b10101111 '
b01100011 (
#37
0&
#38
1&
b00011110 '
b10010110 (
#39
0&
#40
1&
b00010010 '
b11001001 (
#41
0&
#42
1&
b10011010 '
b11111100 (
#43
0&
#44
1&
b11111101 '
b00101111 (
#45
0&
#46
1&
b10110010 '
b01100010 (
#47
0&
#48
1&
b00100000 '
b10010101 (
#49
0&
#50
1&
b00010000 '
b11001000 (
#51
0&
#52
1&
b10010111 '
b11111011 (
#53
0&
#54
1&
b11111101 '
b00101110 (
#55
0&
#56
1&
b10110101 '
b01100001 (
#57
0&
#58
1&
b00100011 '
b10010100 (
#59
0&
#60
1&
b00001110 '
b11000111 (
#61
0&
#62
1&
b10010100 '
b11111010 (
#63
0&
#64
1&
b11111100 '
b00101101 (
#65
0&
#66
1&
b10111000 '
b01100000 (
#67
0&
#68
1&
b00100101 '
b10010011 (
#69
0&
#70
1&
b00001101 '
b11000110 (
#71
0&
#72
1&
b10010001 '
b11111001 (
#73
0&
#74
1&
b11111100 '
b00101100 (
#75
0&
#76
1&
b10111010 '
b01011111 (
#77
0&
#78
1&
b00100111 '
b10010010 (
#79
0&
#80
1&
b00001100 '
b11000101 (
#81
0&
#82
1&
b10001110 '
b11111000 (
#83
0&
#84
1&
b11111011 '
b00101011 (
#85
0&
#86
1&
b10111101 '
b01011110 (
#87
0&
#88
1&
b00101001 '
b10010001 (
#89
0&
#90
1&
b00001010 '
b11000100 (
#91
0&
#92
1&
b10001011 '
b11110111 (
#93
0&
#94
1&
b11111010 '
b00101010 (
#95
0&
#96
1&
b11000000 '
b01011101 (
#97
0&
#98
1&
b00101100 '
b10010000 (
#99
0&
#100
1&
b00001001 '
b11000011 (
#101
0&
#102
1&
b10001000 '
b11110110 (
#103
0&
#104
1&
b11111010 '
b00101001 (
#105
0&
#106
1&
b11000010 '
b01011100 (
#107
0&
#108
1&
b00101110 '
b10001111 (
#109
0&
#110
1&
b00001000 '
b11000010 (
#111
0&
#112
1&
b10000101 '
b11110101 (
#113
0&
#114
1&
b11111001 '
b00101000 (
#115
0&
#116
1&
b11000101 '
b01011011 (
#117
0&
#118
1&
b00110000 '
b10001110 (
#119
0&
#120
1&
b00000111 '
b11000001 (
#121
0&
#122
1&
b10000010 '
b11110100 (
#123
0&
#124
1&
b11111000 '
b00100111 (
#125
0&
#126
1&
b11001000 '
b01011010 (
#127
0&
#128
1&
b00110011 '
b10001101 (
#129
0&
#130
1&
b00000110 '
b11000000 (
#131
0&
#132
1&
b01111111 '
b11110011 (
#133
0&
#134
1&
b11110111 '
b00100110 (
#135
0&
#136
1&
b11001010 '
b01011001 (
#137
0&
#138
1&
b00110101 '
b10001100 (
#139
0&
#140
1&
b00000101 '
b10111111 (
#141
0&
#142
1&
b01111011 '
b11110010 (
#143
0&
#144
1&
b11110110 '
b00100101 (
#145
0&
#146
1&
b11001101 '
b01011000 (
#147
0&
#148
1&
b00111000 '
b10001011 (
#149
0&
#150
1&
b00000100 '
b10111110 (
#151
0&
#152
1&
b01111000 '
b11110001 (
#153
0&
#154
1&
b11110101 '
b00100100 (
#155
0&
#156
1&
b11001111 '
b01010111 (
#157
0&
#158
1&
b00111011 '
b10001010 (
#159
0&
#160
1&
b00000011 '
b10111101 (
#161
0&
#162
1&
b01110101 '
b11110000 (
#163
0&
#164
1&
b11110100 '
b00100011 (
#165
0&
#166
1&
b11010001 '
b01010110 (
#167
0&
#168
1&
b00111101 '
b10001001 (
#169
0&
#170
1&
b00000011 '
b10111100 (
#171
0&
#172
1&
b01110010 '
b11101111 (
#173
0&
#174
1&
b11110011 '
b00100010 (
#175
0&
#176
1&
b11010100 '
b01010101 (
#177
0&
#178
1&
b01000000 '
b10001000 (
#179
0&
#180
1&
b00000010 '
b10111011 (
#181
0&
#182
1&
b01101111 '
b11101110 (
#183
0&
#184
1&
b11110001 '
b00100001 (
#185
0&
#186
1&
b11010110 '
b01010100 (
#187
0&
#188
1&
b01000011 '
b10000111 (
#189
0&
#190
1&
b00000001 '
b10111010 (
#191
0&
#192
1&
b01101100 '
b11101101 (
#193
0&
#194
1&
b11110000 '
b00100000 (
#195
0&
#196
1&
b11011000 '
b01010011 (
#197
0&
#198
1&
b01000101 '
b10000110 (
#199
0&
#200
1&
b00000001 '
b10111001 (
#201
0&
#202
1&
b01101001 '
b11101100 (
#203
0&
#204
1&
b11101111 '
b00011111 (
#205
0&
#206
1&
b11011010 '
b01010010 (
#207
0&
#208
1&
b01001000 '
b10000101 (
#209
0&
#210
1&
b00000000 '
b10111000 (
#211
0&
#212
1&
b01100110 '
b11101011 (
#213
0&
#214
b00110010 #
1&
b11101101 '
b00011110 (
#215
0&
#216
1&
b11011101 '
b01010000 (
#217
0&
#218
1&
b01001110 '
b10000010 (
#219
0&
#220
b00110001 #
1&
b00000000 '
b10110100 (
#221
0&
#222
1&
b01011010 '
b11100101 (
#223
0&
#224
b00110000 #
1&
b11100011 '
b00010110 (
#225
0&
#226
1&
b11101011 '
b01000110 (
#227
0&
#228
1&
b01101100 '
b01110110 (
#229
0&
#230
1&
b00000011 '
b10100110 (
#231
0&
#232
1&
b00110011 '
b11010110 (
#233
0&
#234
1&
b11000000 '
b00000110 (
#235
0&
#236
1&
b11111100 '
b00110110 (
#237
0&
#238
1&
b10011101 '
b01100110 (
#239
0&
#240
1&
b00011000 '
b10010110 (
#241
0&
#242
1&
b00010010 '
b11000110 (
#243
0&
#244
1&
b10010001 '
b11110110 (
#245
0&
#246
1&
b11111010 '
b00100110 (
#247
0&
#248
1&
b11001010 '
b01010110 (
#249
0&
#250
1&
b00111101 '
b10000110 (
#251
0&
#252
1&
b00000001 '
b10110110 (
#253
0&
#254
1&
b01100000 '
b11100110 (
#255
0&
#256
1&
b11100101 '
b00010110 (
#257
0&
#258
1&
b11101011 '
b01000110 (
#259
0&
#260
1&
b01101100 '
b01110110 (
#261
0&
#262
1&
b00000011 '
b10100110 (
#263
0&
#264
b00101111 #
1&
b00110011 '
b11010110 (
#265
0&
#266
1&
b11000000 '
b00000101 (
#267
0&
#268
b00101110 #
1&
b11111101 '
b00110100 (
#269
0&
#270
b00101010 #
1&
b10100011 '
b01100010 (
#271
0&
#272
b00101000 #
1&
b00100000 '
b10001100 (
#273
0&
#274
b00100110 #
1&
b00000101 '
b10110100 (
#275
0&
#276
b00100100 #
1&
b01011010 '
b11011010 (
#277
0&
#278
1&
b11001010 '
b11111110 (
#279
0&
#280
1&
b11111101 '
b00100010 (
#281
0&
#282
1&
b11010100 '
b01000110 (
#283
0&
#284
1&
b01101100 '
b01101010 (
#285
0&
#286
1&
b00010010 '
b10001110 (
#287
0&
#288
1&
b00000111 '
b10110010 (
#289
0&
#290
1&
b01010100 '
b11010110 (
#291
0&
#292
1&
b11000000 '
b11111010 (
#293
0&
#294
1&
b11111100 '
b00011110 (
#295
0&
#296
1&
b11011101 '
b01000010 (
#297
0&
#298
1&
b01111000 '
b01100110 (
#299
0&
#300
1&
b00011000 '
b10001010 (
#301
0&
#302
1&
b00000011 '
b10101110 (
#303
0&
#304
1&
b01001000 '
b11010010 (
#305
0&
#306
1&
b10110101 '
b11110110 (
#307
0&
#308
1&
b11111010 '
b00011010 (
#309
0&
#310
1&
b11100101 '
b00111110 (
#311
0&
#312
1&
b10000101 '
b01100010 (
#313
0&
#314
1&
b00100000 '
b10000110 (
#315
0&
#316
b00100010 #
1&
b00000001 '
b10101010 (
#317
0&
#318
b00100000 #
1&
b00111101 '
b11001100 (
#319
0&
#320
b00011110 #
1&
b10100011 '
b11101100 (
#321
0&
#322
b00011101 #
1&
b11101111 '
b00001010 (
#323
0&
#324
b00011100 #
1&
b11111010 '
b00100111 (
#325
0&
#326
1&
b11001000 '
b01000011 (
#327
0&
#328
1&
b01110101 '
b01011111 (
#329
0&
#330
1&
b00100111 '
b01111011 (
#331
0&
#332
1&
b00000000 '
b10010111 (
#333
0&
#334
1&
b00010011 '
b10110011 (
#335
0&
#336
1&
b01010111 '
b11001111 (
#337
0&
#338
1&
b10101100 '
b11101011 (
#339
0&
#340
1&
b11101101 '
b00000111 (
#341
0&
#342
1&
b11111100 '
b00100011 (
#343
0&
#344
1&
b11010001 '
b00111111 (
#345
0&
#346
1&
b10000010 '
b01011011 (
#347
0&
#348
1&
b00110000 '
b01110111 (
#349
0&
#350
1&
b00000011 '
b10010011 (
#351
0&
#352
1&
b00001101 '
b10101111 (
#353
0&
#354
1&
b01001011 '
b11001011 (
#355
0&
#356
1&
b10100000 '
b11100111 (
#357
0&
#358
1&
b11100110 '
b00000011 (
#359
0&
#360
1&
b11111101 '
b00011111 (
#361
0&
#362
0%
1&
b11011010 '
b00111011 (
#363
0&
#364
1&
b10001110 '
