task2/rom.sv
module rom #(
    parameter   ADDRESS_WIDTH = 8,
                DATA_WIDTH = 8
) (
    input logic clk,
    input logic [ADDRESS_WIDTH-1:0] addr,
    input logic [ADDRESS_WIDTH-1:0] offset,
    output logic [DATA_WIDTH-1:0] dout1,
    output logic [DATA_WIDTH-1:0] dout2
);

logic [DATA_WIDTH-1:0] rom_array [2**ADDRESS_WIDTH-1:0];

initial begin
    $display("Loading ROM:");
    $readmemh("sinerom.mem", rom_array);
end;

always_ff @(posedge clk)
    begin
        // Synchronous output
        dout1 <= rom_array [addr];
        dout2 <= rom_array [addr + offset];
    end

endmodule

task2/counter.sv
module counter #(
    parameter ADDRESS_WIDTH = 8
) (
    input logic [ADDRESS_WIDTH-1:0] incr,
    input logic rst, en, clk,
    output logic [ADDRESS_WIDTH-1:0] count
);

    always_ff @(posedge clk)
        if (rst) count <= 0;
        else if (en) count <= count + incr;
        else count <= count;
endmodule

task2/sinegen.sv
module sinegen(
    input logic [7:0] incr, offset,
    input logic rst, en, clk,
    output logic [7:0] dout1, dout2
);

    logic [7:0] addr;

    counter sinegen_counter (
        .incr (incr),
        .rst (rst),
        .en (en),
        .clk (clk),
        .count (addr)
    );

    rom sinegen_rom (
        .clk (clk),
        .addr (addr),
        .offset (offset),
        .dout1 (dout1),
        .dout2 (dout2)
    );

endmodule

task2/sinegen.vcd
$version Generated by VerilatedVcd $end
$date Fri Oct 24 10:50:48 2025 $end
$timescale 1ps $end

 $scope module TOP $end
  $var wire  1 ' clk $end
  $var wire  8 ( dout1 [7:0] $end
  $var wire  8 ) dout2 [7:0] $end
  $var wire  1 & en $end
  $var wire  8 # incr [7:0] $end
  $var wire  8 $ offset [7:0] $end
  $var wire  1 % rst $end
  $scope module sinegen $end
   $var wire  8 * addr [7:0] $end
   $var wire  1 ' clk $end
   $var wire  8 ( dout1 [7:0] $end
   $var wire  8 ) dout2 [7:0] $end
   $var wire  1 & en $end
   $var wire  8 # incr [7:0] $end
   $var wire  8 $ offset [7:0] $end
   $var wire  1 % rst $end
   $scope module sinegen_counter $end
    $var wire 32 + ADDRESS_WIDTH [31:0] $end
    $var wire  1 ' clk $end
    $var wire  8 * count [7:0] $end
    $var wire  1 & en $end
    $var wire  8 # incr [7:0] $end
    $var wire  1 % rst $end
   $upscope $end
   $scope module sinegen_rom $end
    $var wire 32 + ADDRESS_WIDTH [31:0] $end
    $var wire 32 + DATA_WIDTH [31:0] $end
    $var wire  8 * addr [7:0] $end
    $var wire  1 ' clk $end
    $var wire  8 ( dout1 [7:0] $end
    $var wire  8 ) dout2 [7:0] $end
    $var wire  8 $ offset [7:0] $end
   $upscope $end
  $upscope $end
 $upscope $end
$enddefinitions $end


#0
b00000010 #
b00000001 $
1%
1&
1'
b00000000 (
b00000000 )
b00000000 *
b00000000000000000000000000001000 +
#1
0'
#2
b01000000 $
0%
1'
b11111110 (
b11111101 )
#3
0'
#4
1'
b01111110 )
b00000010 *
#5
0'
#6
1'
b11111101 (
b01111000 )
b00000100 *
#7
0'
#8
1'
b01110010 )
b00000110 *
#9
0'
#10
1'
b11111100 (
b01101100 )
b00001000 *
#11
0'
#12
1'
b11111011 (
b01100110 )
b00001010 *
#13
0'
#14
1'
b11111010 (
b01100000 )
b00001100 *
#15
0'
#16
1'
b11111000 (
b01011010 )
b00001110 *
#17
0'
#18
1'
b11110110 (
b01010100 )
b00010000 *
#19
0'
#20
1'
b11110100 (
b01001110 )
b00010010 *
#21
0'
#22
1'
b11110001 (
b01001000 )
b00010100 *
#23
0'
#24
1'
b11101111 (
b01000011 )
b00010110 *
#25
0'
#26
1'
b11101011 (
b00111101 )
b00011000 *
#27
0'
#28
1'
b11101000 (
b00111000 )
b00011010 *
#29
0'
#30
1'
b11100101 (
b00110011 )
b00011100 *
#31
0'
#32
1'
b11100001 (
b00101110 )
b00011110 *
#33
0'
#34
1'
b11011101 (
b00101001 )
b00100000 *
#35
0'
#36
1'
b11011000 (
b00100101 )
b00100010 *
#37
0'
#38
1'
b11010100 (
b00100000 )
b00100100 *
#39
0'
#40
1'
b11001111 (
b00011100 )
b00100110 *
#41
0'
#42
1'
b11001010 (
b00011000 )
b00101000 *
#43
0'
#44
1'
b11000101 (
b00010101 )
b00101010 *
#45
0'
#46
1'
b11000000 (
b00010010 )
b00101100 *
#47
0'
#48
1'
b10111010 (
b00001110 )
b00101110 *
#49
0'
#50
1'
b10110101 (
b00001100 )
b00110000 *
#51
0'
#52
1'
b10101111 (
b00001001 )
b00110010 *
#53
0'
#54
1'
b10101001 (
b00000111 )
b00110100 *
#55
0'
#56
1'
b10100011 (
b00000101 )
b00110110 *
#57
0'
#58
1'
b10011101 (
b00000011 )
b00111000 *
#59
0'
#60
1'
b10010111 (
b00000010 )
b00111010 *
#61
0'
#62
1'
b10010001 (
b00000001 )
b00111100 *
#63
0'
#64
1'
b10001011 (
b00000000 )
b00111110 *
#65
0'
#66
1'
b10000101 (
b01000000 *
#67
0'
#68
1'
b01111110 (
b01000010 *
#69
0'
#70
1'
b01111000 (
b01000100 *
#71
0'
#72
1'
b01110010 (
b01000110 *
#73
0'
#74
1'
b01101100 (
b00000001 )
b01001000 *
#75
0'
#76
1'
b01100110 (
b00000010 )
b01001010 *
#77
0'
#78
1'
b01100000 (
b00000011 )
b01001100 *
#79
0'
#80
1'
b01011010 (
b00000101 )
b01001110 *
#81
0'
#82
1'
b01010100 (
b00000111 )
b01010000 *
#83
0'
#84
1'
b01001110 (
b00001001 )
b01010010 *
#85
0'
#86
1'
b01001000 (
b00001100 )
b01010100 *
#87
0'
#88
1'
b01000011 (
b00001110 )
b01010110 *
#89
0'
#90
1'
b00111101 (
b00010010 )
b01011000 *
#91
0'
#92
1'
b00111000 (
b00010101 )
b01011010 *
#93
0'
#94
1'
b00110011 (
b00011000 )
b01011100 *
#95
0'
#96
1'
b00101110 (
b00011100 )
b01011110 *
#97
0'
#98
1'
b00101001 (
b00100000 )
b01100000 *
#99
0'
#100
1'
b00100101 (
b00100101 )
b01100010 *
#101
0'
#102
1'
b00100000 (
b00101001 )
b01100100 *
#103
0'
#104
1'
b00011100 (
b00101110 )
b01100110 *
#105
0'
#106
1'
b00011000 (
b00110011 )
b01101000 *
#107
0'
#108
1'
b00010101 (
b00111000 )
b01101010 *
#109
0'
#110
1'
b00010010 (
b00111101 )
b01101100 *
#111
0'
#112
1'
b00001110 (
b01000011 )
b01101110 *
#113
0'
#114
1'
b00001100 (
b01001000 )
b01110000 *
#115
0'
#116
1'
b00001001 (
b01001110 )
b01110010 *
#117
0'
#118
1'
b00000111 (
b01010100 )
b01110100 *
#119
0'
#120
1'
b00000101 (
b01011010 )
b01110110 *
#121
0'
#122
1'
b00000011 (
b01100000 )
b01111000 *
#123
0'
#124
1'
b00000010 (
b01100110 )
b01111010 *
#125
0'
#126
1'
b00000001 (
b01101100 )
b01111100 *
#127
0'
#128
1'
b00000000 (
b01110010 )
b01111110 *
#129
0'
#130
1'
b01111000 )
b10000000 *
#131
0'
#132
1'
b01111111 )
b10000010 *
#133
0'
#134
1'
b10000101 )
b10000100 *
#135
0'
#136
1'
b10001011 )
b10000110 *
#137
0'
#138
1'
b00000001 (
b10010001 )
b10001000 *
#139
0'
#140
1'
b00000010 (
b10010111 )
b10001010 *
#141
0'
#142
1'
b00000011 (
b10011101 )
b10001100 *
#143
0'
#144
1'
b00000101 (
b10100011 )
b10001110 *
#145
0'
#146
1'
b00000111 (
b10101001 )
b10010000 *
#147
0'
#148
1'
b00001001 (
b10101111 )
b10010010 *
#149
0'
#150
1'
b00001100 (
b10110101 )
b10010100 *
#151
0'
#152
1'
b00001110 (
b10111010 )
b10010110 *
#153
0'
#154
1'
b00010010 (
b11000000 )
b10011000 *
#155
0'
#156
1'
b00010101 (
b11000101 )
b10011010 *
#157
0'
#158
1'
b00011000 (
b11001010 )
b10011100 *
#159
0'
#160
1'
b00011100 (
b11001111 )
b10011110 *
#161
0'
#162
1'
b00100000 (
b11010100 )
b10100000 *
#163
0'
#164
1'
b00100101 (
b11011000 )
b10100010 *
#165
0'
#166
1'
b00101001 (
b11011101 )
b10100100 *
#167
0'
#168
1'
b00101110 (
b11100001 )
b10100110 *
#169
0'
#170
1'
b00110011 (
b11100101 )
b10101000 *
#171
0'
#172
1'
b00111000 (
b11101000 )
b10101010 *
#173
0'
#174
1'
b00111101 (
b11101011 )
b10101100 *
#175
0'
#176
1'
b01000011 (
b11101111 )
b10101110 *
#177
0'
#178
1'
b01001000 (
b11110001 )
b10110000 *
#179
0'
#180
1'
b01001110 (
b11110100 )
b10110010 *
#181
0'
#182
1'
b01010100 (
b11110110 )
b10110100 *
#183
0'
#184
1'
b01011010 (
b11111000 )
b10110110 *
#185
0'
#186
1'
b01100000 (
b11111010 )
b10111000 *
#187
0'
#188
1'
b01100110 (
b11111011 )
b10111010 *
#189
0'
#190
1'
b01101100 (
b11111100 )
b10111100 *
#191
0'
#192
1'
b01110010 (
b11111101 )
b10111110 *
#193
0'
#194
1'
b01111000 (
b11000000 *
#195
0'
#196
1'
b01111111 (
b11111110 )
b11000010 *
#197
0'
#198
1'
b10000101 (
b11111101 )
b11000100 *
#199
0'
#200
1'
b10001011 (
b11000110 *
#201
0'
#202
1'
b10010001 (
b11111100 )
b11001000 *
#203
0'
#204
1'
b10010111 (
b11111011 )
b11001010 *
#205
0'
#206
1'
b10011101 (
b11111010 )
b11001100 *
#207
0'
#208
1'
b10100011 (
b11111000 )
b11001110 *
#209
0'
#210
1'
b10101001 (
b11110110 )
b11010000 *
#211
0'
#212
1'
b10101111 (
b11110100 )
b11010010 *
#213
0'
#214
1'
b10110101 (
b11110001 )
b11010100 *
#215
0'
#216
1'
b10111010 (
b11101111 )
b11010110 *
#217
0'
#218
1'
b11000000 (
b11101011 )
b11011000 *
#219
0'
#220
1'
b11000101 (
b11101000 )
b11011010 *
#221
0'
#222
1'
b11001010 (
b11100101 )
b11011100 *
#223
0'
#224
1'
b11001111 (
b11100001 )
b11011110 *
#225
0'
#226
1'
b11010100 (
b11011101 )
b11100000 *
#227
0'
#228
1'
b11011000 (
b11011000 )
b11100010 *
#229
0'
#230
1'
b11011101 (
b11010100 )
b11100100 *
#231
0'
#232
1'
b11100001 (
b11001111 )
b11100110 *
#233
0'
#234
1'
b11100101 (
b11001010 )
b11101000 *
#235
0'
#236
1'
b11101000 (
b11000101 )
b11101010 *
#237
0'
#238
1'
b11101011 (
b11000000 )
b11101100 *
#239
0'
#240
1'
b11101111 (
b10111010 )
b11101110 *
#241
0'
#242
1'
b11110001 (
b10110101 )
b11110000 *
#243
0'
#244
1'
b11110100 (
b10101111 )
b11110010 *
#245
0'
#246
1'
b11110110 (
b10101001 )
b11110100 *
#247
0'
#248
1'
b11111000 (
b10100011 )
b11110110 *
#249
0'
#250
1'
b11111010 (
b10011101 )
b11111000 *
#251
0'
#252
1'
b11111011 (
b10010111 )
b11111010 *
#253
0'
#254
1'
b11111100 (
b10010001 )
b11111100 *
#255
0'
#256
1'
b11111101 (
b10001011 )
b11111110 *
#257
0'
#258
1'
b10000101 )
b00000000 *
#259
0'
#260
1'
b11111110 (
b01111110 )
b00000010 *
#261
0'
#262
1'
b11111101 (
b01111000 )
b00000100 *
#263
0'
#264
1'
b01110010 )
b00000110 *
#265
0'
#266
1'
b11111100 (
b01101100 )
b00001000 *
#267
0'
#268
1'
b11111011 (
b01100110 )
b00001010 *
#269
0'
#270
1'
b11111010 (
b01100000 )
b00001100 *
#271
0'
#272
1'
b11111000 (
b01011010 )
b00001110 *
#273
0'
#274
1'
b11110110 (
b01010100 )
b00010000 *
#275
0'
#276
1'
b11110100 (
b01001110 )
b00010010 *
#277
0'
#278
1'
b11110001 (
b01001000 )
b00010100 *
#279
0'
#280
1'
b11101111 (
b01000011 )
b00010110 *
#281
0'
#282
1'
b11101011 (
b00111101 )
b00011000 *
#283
0'
#284
1'
b11101000 (
b00111000 )
b00011010 *
#285
0'
#286
1'
b11100101 (
b00110011 )
b00011100 *
#287
0'
#288
1'
b11100001 (
b00101110 )
b00011110 *
#289
0'
#290
1'
b11011101 (
b00101001 )
b00100000 *
#291
0'
#292
1'
b11011000 (
b00100101 )
b00100010 *
#293
0'
#294
1'
b11010100 (
b00100000 )
b00100100 *
#295
0'
#296
1'
b11001111 (
b00011100 )
b00100110 *
#297
0'
#298
1'
b11001010 (
b00011000 )
b00101000 *
#299
0'
#300
1'
b11000101 (
b00010101 )
b00101010 *
#301
0'
#302
1'
b11000000 (
b00010010 )
b00101100 *
#303
0'
#304
1'
b10111010 (
b00001110 )
b00101110 *
#305
0'
#306
1'
b10110101 (
b00001100 )
b00110000 *
#307
0'
#308
1'
b10101111 (
b00001001 )
b00110010 *
#309
0'
#310
1'
b10101001 (
b00000111 )
b00110100 *
#311
0'
#312
1'
b10100011 (
b00000101 )
b00110110 *
#313
0'
#314
1'
b10011101 (
b00000011 )
b00111000 *
#315
0'
#316
1'
b10010111 (
b00000010 )
b00111010 *
#317
0'
#318
1'
b10010001 (
b00000001 )
b00111100 *
#319
0'
#320
1'
b10001011 (
b00000000 )
b00111110 *
#321
0'
#322
1'
b10000101 (
b01000000 *
#323
0'
#324
1'
b01111110 (
b01000010 *
#325
0'
#326
1'
b01111000 (
b01000100 *
#327
0'
#328
1'
b01110010 (
b01000110 *
#329
0'
#330
1'
b01101100 (
b00000001 )
b01001000 *
#331
0'
#332
1'
b01100110 (
b00000010 )
b01001010 *
#333
0'
#334
1'
b01100000 (
b00000011 )
b01001100 *
#335
0'
#336
1'
b01011010 (
b00000101 )
b01001110 *
#337
0'
#338
1'
b01010100 (
b00000111 )
b01010000 *
#339
0'
#340
1'
b01001110 (
b00001001 )
b01010010 *
#341
0'
#342
1'
b01001000 (
b00001100 )
b01010100 *
#343
0'
#344
1'
b01000011 (
b00001110 )
b01010110 *
#345
0'
#346
1'
b00111101 (
b00010010 )
b01011000 *
#347
0'
#348
1'
b00111000 (
b00010101 )
b01011010 *
#349
0'
#350
1'
b00110011 (
b00011000 )
b01011100 *
#351
0'
#352
1'
b00101110 (
b00011100 )
b01011110 *
#353
0'
#354
1'
b00101001 (
b00100000 )
b01100000 *
#355
0'
#356
1'
b00100101 (
b00100101 )
b01100010 *
#357
0'
#358
1'
b00100000 (
b00101001 )
b01100100 *
#359
0'
#360
1'
b00011100 (
b00101110 )
b01100110 *
#361
0'
#362
1'
b00011000 (
b00110011 )
b01101000 *
#363
0'
#364
1'
b00010101 (
b00111000 )
b01101010 *
#365
0'
#366
1'
b00010010 (
b00111101 )
b01101100 *
#367
0'
#368
1'
b00001110 (
b01000011 )
b01101110 *
#369
0'
#370
1'
b00001100 (
b01001000 )
b01110000 *
#371
0'
#372
1'
b00001001 (
b01001110 )
b01110010 *
#373
0'
#374
1'
b00000111 (
b01010100 )
b01110100 *
#375
0'
#376
1'
b00000101 (
b01011010 )
b01110110 *
#377
0'
#378
1'
b00000011 (
b01100000 )
b01111000 *
#379
0'
#380
1'
b00000010 (
b01100110 )
b01111010 *
#381
0'
#382
1'
b00000001 (
b01101100 )
b01111100 *
#383
0'
#384
1'
b00000000 (
b01110010 )
b01111110 *
#385
0'
#386
1'
b01111000 )
b10000000 *
#387
0'
#388
1'
b01111111 )
b10000010 *
#389
0'
#390
1'
b10000101 )
b10000100 *
#391
0'
#392
1'
b10001011 )
b10000110 *
#393
0'
#394
1'
b00000001 (
b10010001 )
b10001000 *
#395
0'
#396
1'
b00000010 (
b10010111 )
b10001010 *
#397
0'
#398
1'
b00000011 (
b10011101 )
b10001100 *
#399
0'
#400
1'
b00000101 (
b10100011 )
b10001110 *
#401
0'
#402
1'
b00000111 (
b10101001 )
b10010000 *
#403
0'
#404
1'
b00001001 (
b10101111 )
b10010010 *
#405
0'
#406
1'
b00001100 (
b10110101 )
b10010100 *
#407
0'
#408
1'
b00001110 (
b10111010 )
b10010110 *
#409
0'
#410
1'
b00010010 (
b11000000 )
b10011000 *
#411
0'
#412
1'
b00010101 (
b11000101 )
b10011010 *
#413
0'
#414
1'
b00011000 (
b11001010 )
b10011100 *
#415
0'
#416
1'
b00011100 (
b11001111 )
b10011110 *
#417
0'
#418
1'
b00100000 (
b11010100 )
b10100000 *
#419
0'
#420
1'
b00100101 (
b11011000 )
b10100010 *
#421
0'
#422
1'
b00101001 (
b11011101 )
b10100100 *
#423
0'
#424
1'
b00101110 (
b11100001 )
b10100110 *
#425
0'
#426
1'
b00110011 (
b11100101 )
b10101000 *
#427
0'
#428
1'
b00111000 (
b11101000 )
b10101010 *
#429
0'
#430
1'
b00111101 (
b11101011 )
b10101100 *
#431
0'
#432
1'
b01000011 (
b11101111 )
b10101110 *
#433
0'
#434
1'
b01001000 (
b11110001 )
b10110000 *
#435
0'
#436
1'
b01001110 (
b11110100 )
b10110010 *
#437
0'
#438
1'
b01010100 (
b11110110 )
b10110100 *
#439
0'
#440
1'
b01011010 (
b11111000 )
b10110110 *
#441
0'
#442
1'
b01100000 (
b11111010 )
b10111000 *
#443
0'
#444
1'
b01100110 (
b11111011 )
b10111010 *
#445
0'
#446
1'
b01101100 (
b11111100 )
b10111100 *
#447
0'
#448
1'
b01110010 (
b11111101 )
b10111110 *
#449
0'
#450
1'
b01111000 (
b11000000 *
#451
0'
#452
1'
b01111111 (
b11111110 )
b11000010 *
#453
0'
#454
1'
b10000101 (
b11111101 )
b11000100 *
#455
0'
#456
1'
b10001011 (
b11000110 *
#457
0'
#458
1'
b10010001 (
b11111100 )
b11001000 *
#459
0'
#460
1'
b10010111 (
b11111011 )
b11001010 *
#461
0'
#462
1'
b10011101 (
b11111010 )
b11001100 *
#463
0'
#464
1'
b10100011 (
b11111000 )
b11001110 *
#465
0'
#466
1'
b10101001 (
b11110110 )
b11010000 *
#467
0'
#468
1'
b10101111 (
b11110100 )
b11010010 *
#469
0'
#470
1'
b10110101 (
b11110001 )
b11010100 *
#471
0'
#472
1'
b10111010 (
b11101111 )
b11010110 *
#473
0'
#474
1'
b11000000 (
b11101011 )
b11011000 *
#475
0'
#476
1'
b11000101 (
b11101000 )
b11011010 *
#477
0'
#478
1'
b11001010 (
b11100101 )
b11011100 *
#479
0'
#480
1'
b11001111 (
b11100001 )
b11011110 *
#481
0'
#482
1'
b11010100 (
b11011101 )
b11100000 *
#483
0'
#484
1'
b11011000 (
b11011000 )
b11100010 *
#485
0'
#486
1'
b11011101 (
b11010100 )
b11100100 *
#487
0'
#488
1'
b11100001 (
b11001111 )
b11100110 *
#489
0'
#490
1'
b11100101 (
b11001010 )
b11101000 *
#491
0'
#492
1'
b11101000 (
b11000101 )
b11101010 *
#493
0'
#494
1'
b11101011 (
b11000000 )
b11101100 *
#495
0'
#496
1'
b11101111 (
b10111010 )
b11101110 *
#497
0'
#498
1'
b11110001 (
b10110101 )
b11110000 *
#499
0'
#500
1'
b11110100 (
b10101111 )
b11110010 *
#501
0'
#502
1'
b11110110 (
b10101001 )
b11110100 *
#503
0'
#504
1'
b11111000 (
b10100011 )
b11110110 *
#505
0'
#506
1'
b11111010 (
b10011101 )
b11111000 *
#507
0'
#508
1'
b11111011 (
b10010111 )
b11111010 *
#509
0'
#510
1'
b11111100 (
b10010001 )
b11111100 *
#511
0'
#512
1'
b11111101 (
b10001011 )
b11111110 *
#513
0'
#514
1'
b10000101 )
b00000000 *
#515
0'
#516
1'
b11111110 (
b01111110 )
b00000010 *
#517
0'
#518
1'
b11111101 (
b01111000 )
b00000100 *
#519
0'
#520
1'
b01110010 )
b00000110 *
#521
0'
#522
1'
b11111100 (
b01101100 )
b00001000 *
#523
0'
#524
1'
b11111011 (
b01100110 )
b00001010 *
#525
0'
#526
1'
b11111010 (
b01100000 )
b00001100 *
#527
0'
#528
1'
b11111000 (
b01011010 )
b00001110 *
#529
0'
#530
1'
b11110110 (
b01010100 )
b00010000 *
#531
0'
#532
1'
b11110100 (
b01001110 )
b00010010 *
#533
0'
#534
1'
b11110001 (
b01001000 )
b00010100 *
#535
0'
#536
1'
b11101111 (
b01000011 )
b00010110 *
#537
0'
#538
1'
b11101011 (
b00111101 )
b00011000 *
#539
0'
#540
1'
b11101000 (
b00111000 )
b00011010 *
#541
0'
#542
1'
b11100101 (
b00110011 )
b00011100 *
#543
0'
#544
1'
b11100001 (
b00101110 )
b00011110 *
#545
0'
#546
1'
b11011101 (
b00101001 )
b00100000 *
#547
0'
#548
1'
b11011000 (
b00100101 )
b00100010 *
#549
0'
#550
1'
b11010100 (
b00100000 )
b00100100 *
#551
0'
#552
1'
b11001111 (
b00011100 )
b00100110 *
#553
0'
#554
1'
b11001010 (
b00011000 )
b00101000 *
#555
0'
#556
1'
b11000101 (
b00010101 )
b00101010 *
#557
0'
#558
1'
b11000000 (
b00010010 )
b00101100 *
#559
0'
#560
1'
b10111010 (
b00001110 )
b00101110 *
#561
0'
#562
1'
b10110101 (
b00001100 )
b00110000 *
#563
0'
#564
1'
b10101111 (
b00001001 )
b00110010 *
#565
0'
#566
1'
b10101001 (
b00000111 )
b00110100 *
#567
0'
#568
1'
b10100011 (
b00000101 )
b00110110 *
#569
0'
#570
1'
b10011101 (
b00000011 )
b00111000 *
#571
0'
#572
1'
b10010111 (
b00000010 )
b00111010 *
#573
0'
#574
1'
b10010001 (
b00000001 )
b00111100 *
#575
0'
#576
1'
b10001011 (
b00000000 )
b00111110 *
#577
0'
#578
1'
b10000101 (
b01000000 *
#579
0'
#580
1'
b01111110 (
b01000010 *
#581
0'
#582
1'
b01111000 (
b01000100 *
#583
0'
#584
1'
b01110010 (
b01000110 *
#585
0'
#586
1'
b01101100 (
b00000001 )
b01001000 *
#587
0'
#588
1'
b01100110 (
b00000010 )
b01001010 *
#589
0'
#590
1'
b01100000 (
b00000011 )
b01001100 *
#591
0'
#592
1'
b01011010 (
b00000101 )
b01001110 *
#593
0'
#594
1'
b01010100 (
b00000111 )
b01010000 *
#595
0'
#596
1'
b01001110 (
b00001001 )
b01010010 *
#597
0'
#598
1'
b01001000 (
b00001100 )
b01010100 *
#599
0'
#600
1'
b01000011 (
b00001110 )
b01010110 *
#601
0'
#602
1'
b00111101 (
b00010010 )
b01011000 *
#603
0'
#604
1'
b00111000 (
b00010101 )
b01011010 *
#605
0'
#606
1'
b00110011 (
b00011000 )
b01011100 *
#607
0'
#608
1'
b00101110 (
b00011100 )
b01011110 *
#609
0'
#610
1'
b00101001 (
b00100000 )
b01100000 *
#611
0'
#612
1'
b00100101 (
b00100101 )
b01100010 *
#613
0'
#614
1'
b00100000 (
b00101001 )
b01100100 *
#615
0'
#616
1'
b00011100 (
b00101110 )
b01100110 *
#617
0'
#618
1'
b00011000 (
b00110011 )
b01101000 *
#619
0'
#620
1'
b00010101 (
b00111000 )
b01101010 *
#621
0'
#622
1'
b00010010 (
b00111101 )
b01101100 *
#623
0'
#624
1'
b00001110 (
b01000011 )
b01101110 *
#625
0'
#626
1'
b00001100 (
b01001000 )
b01110000 *
#627
0'
#628
1'
b00001001 (
b01001110 )
b01110010 *
#629
0'
#630
1'
b00000111 (
b01010100 )
b01110100 *
#631
0'
#632
1'
b00000101 (
b01011010 )
b01110110 *
#633
0'
#634
1'
b00000011 (
b01100000 )
b01111000 *
#635
0'
#636
1'
b00000010 (
b01100110 )
b01111010 *
#637
0'
#638
1'
b00000001 (
b01101100 )
b01111100 *
#639
0'
#640
1'
b00000000 (
b01110010 )
b01111110 *
#641
0'
#642
1'
b01111000 )
b10000000 *
#643
0'
#644
1'
b01111111 )
b10000010 *
#645
0'
#646
1'
b10000101 )
b10000100 *
#647
0'
#648
1'
b10001011 )
b10000110 *
#649
0'
#650
1'
b00000001 (
b10010001 )
b10001000 *
#651
0'
#652
1'
b00000010 (
b10010111 )
b10001010 *
#653
0'
#654
1'
b00000011 (
b10011101 )
b10001100 *
#655
0'
#656
1'
b00000101 (
b10100011 )
b10001110 *
#657
0'
#658
1'
b00000111 (
b10101001 )
b10010000 *
#659
0'
#660
1'
b00001001 (
b10101111 )
b10010010 *
#661
0'
#662
1'
b00001100 (
b10110101 )
b10010100 *
#663
0'
#664
1'
b00001110 (
b10111010 )
b10010110 *
#665
0'
#666
1'
b00010010 (
b11000000 )
b10011000 *
#667
0'
#668
1'
b00010101 (
b11000101 )
b10011010 *
#669
0'
#670
1'
b00011000 (
b11001010 )
b10011100 *
#671
0'
#672
1'
b00011100 (
b11001111 )
b10011110 *
#673
0'
#674
1'
b00100000 (
b11010100 )
b10100000 *
#675
0'
#676
1'
b00100101 (
b11011000 )
b10100010 *
#677
0'
#678
1'
b00101001 (
b11011101 )
b10100100 *
#679
0'
#680
1'
b00101110 (
b11100001 )
b10100110 *
#681
0'
#682
1'
b00110011 (
b11100101 )
b10101000 *
#683
0'
#684
1'
b00111000 (
b11101000 )
b10101010 *
#685
0'
#686
1'
b00111101 (
b11101011 )
b10101100 *
#687
0'
#688
1'
b01000011 (
b11101111 )
b10101110 *
#689
0'
#690
1'
b01001000 (
b11110001 )
b10110000 *
#691
0'
#692
1'
b01001110 (
b11110100 )
b10110010 *
#693
0'
#694
1'
b01010100 (
b11110110 )
b10110100 *
#695
0'
#696
1'
b01011010 (
b11111000 )
b10110110 *
#697
0'
#698
1'
b01100000 (
b11111010 )
b10111000 *
#699
0'
#700
1'
b01100110 (
b11111011 )
b10111010 *
#701
0'
#702
1'
b01101100 (
b11111100 )
b10111100 *
#703
0'
#704
1'
b01110010 (
b11111101 )
b10111110 *
#705
0'
#706
1'
b01111000 (
b11000000 *
#707
0'
#708
1'
b01111111 (
b11111110 )
b11000010 *
#709
0'
#710
1'
b10000101 (
b11111101 )
b11000100 *
#711
0'
#712
1'
b10001011 (
b11000110 *
#713
0'
#714
1'
b10010001 (
b11111100 )
b11001000 *
#715
0'
#716
1'
b10010111 (
b11111011 )
b11001010 *
#717
0'
#718
1'
b10011101 (
b11111010 )
b11001100 *
#719
0'
#720
1'
b10100011 (
b11111000 )
b11001110 *
#721
0'
#722
1'
b10101001 (
b11110110 )
b11010000 *
#723
0'
#724
1'
b10101111 (
b11110100 )
b11010010 *
#725
0'
#726
1'
b10110101 (
b11110001 )
b11010100 *
#727
0'
#728
1'
b10111010 (
b11101111 )
b11010110 *
#729
0'
#730
1'
b11000000 (
b11101011 )
b11011000 *
#731
0'
#732
1'
b11000101 (
b11101000 )
b11011010 *
#733
0'
#734
1'
b11001010 (
b11100101 )
b11011100 *
#735
0'
#736
1'
b11001111 (
b11100001 )
b11011110 *
#737
0'
#738
1'
b11010100 (
b11011101 )
b11100000 *
#739
0'
#740
1'
b11011000 (
b11011000 )
b11100010 *
#741
0'
#742
1'
b11011101 (
b11010100 )
b11100100 *
#743
0'
#744
1'
b11100001 (
b11001111 )
b11100110 *
#745
0'
#746
1'
b11100101 (
b11001010 )
b11101000 *
#747
0'
#748
1'
b11101000 (
b11000101 )
b11101010 *
#749
0'
#750
1'
b11101011 (
b11000000 )
b11101100 *
#751
0'
#752
1'
b11101111 (
b10111010 )
b11101110 *
#753
0'
#754
1'
b11110001 (
b10110101 )
b11110000 *
#755
0'
#756
1'
b11110100 (
b10101111 )
b11110010 *
#757
0'
#758
1'
b11110110 (
b10101001 )
b11110100 *
#759
0'
#760
1'
b11111000 (
b10100011 )
b11110110 *
#761
0'
#762
1'
b11111010 (
b10011101 )
b11111000 *
#763
0'
#764
1'
b11111011 (
b10010111 )
b11111010 *
#765
0'
#766
1'
b11111100 (
b10010001 )
b11111100 *
#767
0'
#768
1'
b11111101 (
b10001011 )
b11111110 *
#769
0'
#770
1'
b10000101 )
b00000000 *
#771
0'
#772
1'
b11111110 (
b01111110 )
b00000010 *
#773
0'
#774
1'
b11111101 (
b01111000 )
b00000100 *
#775
0'
#776
1'
b01110010 )
b00000110 *
#777
0'
#778
1'
b11111100 (
b01101100 )
b00001000 *
#779
0'
#780
1'
b11111011 (
b01100110 )
b00001010 *
#781
0'
#782
1'
b11111010 (
b01100000 )
b00001100 *
#783
0'
#784
1'
b11111000 (
b01011010 )
b00001110 *
#785
0'
#786
1'
b11110110 (
b01010100 )
b00010000 *
#787
0'
#788
1'
b11110100 (
b01001110 )
b00010010 *
#789
0'
#790
1'
b11110001 (
b01001000 )
b00010100 *
#791
0'
#792
1'
b11101111 (
b01000011 )
b00010110 *
#793
0'
#794
1'
b11101011 (
b00111101 )
b00011000 *
#795
0'
#796
1'
b11101000 (
b00111000 )
b00011010 *
#797
0'
#798
1'
b11100101 (
b00110011 )
b00011100 *
#799
0'
#800
1'
b11100001 (
b00101110 )
b00011110 *
#801
0'
#802
1'
b11011101 (
b00101001 )
b00100000 *
#803
0'
#804
1'
b11011000 (
b00100101 )
b00100010 *
#805
0'
#806
1'
b11010100 (
b00100000 )
b00100100 *
#807
0'
#808
1'
b11001111 (
b00011100 )
b00100110 *
#809
0'
#810
1'
b11001010 (
b00011000 )
b00101000 *
#811
0'
#812
1'
b11000101 (
b00010101 )
b00101010 *
#813
0'
#814
1'
b11000000 (
b00010010 )
b00101100 *
#815
0'
#816
1'
b10111010 (
b00001110 )
b00101110 *
#817
0'
#818
1'
b10110101 (
b00001100 )
b00110000 *
#819
0'
#820
1'
b10101111 (
b00001001 )
b00110010 *
#821
0'
#822
1'
b10101001 (
b00000111 )
b00110100 *
#823
0'
#824
1'
b10100011 (
b00000101 )
b00110110 *
#825
0'
#826
1'
b10011101 (
b00000011 )
b00111000 *
#827
0'
#828
1'
b10010111 (
b00000010 )
b00111010 *
#829
0'
#830
1'
b10010001 (
b00000001 )
b00111100 *
#831
0'
#832
1'
b10001011 (
b00000000 )
b00111110 *
#833
0'
#834
1'
b10000101 (
b01000000 *
#835
0'
#836
1'
b01111110 (
b01000010 *
#837
0'
#838
1'
b01111000 (
b01000100 *
#839
0'
#840
1'
b01110010 (
b01000110 *
